.flake8
.gitignore
.pylintrc
MANIFEST.in
README.md
setup.cfg
setup.py
test.sh
dist-libcx/Makefile.am
dist-libcx/Makefile.in
dist-libcx/aclocal.m4
dist-libcx/autogen.sh
dist-libcx/config.h.in
dist-libcx/configure
dist-libcx/configure.ac
dist-libcx/cx.pc.in
dist-libcx/build-aux/ar-lib
dist-libcx/build-aux/compile
dist-libcx/build-aux/config.guess
dist-libcx/build-aux/config.sub
dist-libcx/build-aux/depcomp
dist-libcx/build-aux/install-sh
dist-libcx/build-aux/ltmain.sh
dist-libcx/build-aux/missing
dist-libcx/build-aux/test-driver
dist-libcx/include/Makefile.am
dist-libcx/include/Makefile.in
dist-libcx/include/cx.h
dist-libcx/include/cx/asn1.h
dist-libcx/include/cx/drbg.h
dist-libcx/include/cx/generator.h
dist-libcx/include/cx/preseed.h
dist-libcx/include/cx/seedcalc.h
dist-libcx/include/cx/seedrep.h
dist-libcx/m4/libtool.m4
dist-libcx/m4/ltoptions.m4
dist-libcx/m4/ltsugar.m4
dist-libcx/m4/ltversion.m4
dist-libcx/m4/lt~obsolete.m4
dist-libcx/src/Makefile.am
dist-libcx/src/Makefile.am.asn1
dist-libcx/src/Makefile.in
dist-libcx/src/asn1.c
dist-libcx/src/cxtest.c
dist-libcx/src/cxtest.h
dist-libcx/src/debug.h
dist-libcx/src/drbg.c
dist-libcx/src/generator.c
dist-libcx/src/gentest.c
dist-libcx/src/gentest.h
dist-libcx/src/linktest.c
dist-libcx/src/preseed.c
dist-libcx/src/preseedtest.c
dist-libcx/src/preseedtest.h
dist-libcx/src/seedcalc.c
dist-libcx/src/seedcalctest.c
dist-libcx/src/seedcalctest.h
dist-libcx/src/seedrep.c
dist-libcx/src/seedreptest.c
dist-libcx/src/seedreptest.h
dist-libcx/src/asn1/ANY.c
dist-libcx/src/asn1/ANY.h
dist-libcx/src/asn1/AlertLevel.c
dist-libcx/src/asn1/AlertLevel.h
dist-libcx/src/asn1/AlgorithmIdentifier.c
dist-libcx/src/asn1/AlgorithmIdentifier.h
dist-libcx/src/asn1/BIT_STRING.c
dist-libcx/src/asn1/BIT_STRING.h
dist-libcx/src/asn1/BOOLEAN.c
dist-libcx/src/asn1/BOOLEAN.h
dist-libcx/src/asn1/ContentInfo.c
dist-libcx/src/asn1/ContentInfo.h
dist-libcx/src/asn1/ContentType.c
dist-libcx/src/asn1/ContentType.h
dist-libcx/src/asn1/Extension.c
libcx.egg-info/PKG-INFO
libcx.egg-info/SOURCES.txt
libcx.egg-info/dependency_links.txt
libcx.egg-info/not-zip-safe
libcx.egg-info/requires.txt
libcx.egg-info/top_level.txt
